{
 "descripcion": "Comprobar que el estudiante sabe diferenciar variables numericos",
 "calificacionMin": 3,
 "ratingsTotales": 0,
 "actividadesSigExitoso": [],
 "actividadesPrereqs": [],
 "preguntasAbiertas": [
  "Cual es la diferencia entre double y float?",
  "Se puede pasar de un double a un int o de un int a un double? Por que o por que no?",
  "Diga cual es su tipo de variable favorita y justifique."
 ],
 "rating": 0,
 "datosEstudiantes": [
  "DatoEstudiante_73d084cb-cf15-4847-9e95-a062b4e25491",
  "DatoEstudiante_d35d41f6-71fe-4de0-b703-2e60622cd570"
 ],
 "resenias": [],
 "type": "Examen",
 "nombre": "Tipos de variables examen",
 "fechaLim": [
  0,
  1,
  0
 ],
 "objetivos": [
  "Saber que es un int",
  "Saber que es un double",
  "Saber que es un float"
 ],
 "actividadesSigFracaso": [],
 "duracion": 30,
 "obligatoria": true,
 "creadorID": "Profesor-KakashiCentralPersistenciaTest",
 "id": "Actividaddbea122c-1fe4-45e8-8860-f7482e7ac91f",
 "dificultad": 2.5
}