{
 "descripcion": "Una lectura para saber los tipos de variable",
 "instrucciones": "Lea el articulo",
 "recurso": "https://www.w3schools.com/python/python_datatypes.asp",
 "ratingsTotales": 0,
 "actividadesSigExitoso": [],
 "actividadesPrereqs": [],
 "rating": 0,
 "datosEstudiantes": [
  "DatoEstudiante_8f7a58d2-162f-47af-a853-d0987e93c660",
  "DatoEstudiante_58d78c24-34e7-472b-a2d7-e61d6d603177"
 ],
 "resenias": [],
 "type": "Actividad recurso",
 "nombre": "Lectura de variables",
 "fechaLim": [
  0,
  0,
  0
 ],
 "objetivos": [
  "Saber que es un int",
  "Saber que es un double",
  "Saber que es un float"
 ],
 "duracion": 20,
 "obligatoria": true,
 "creadorID": "Profesor-KakashiCentralPersistenciaTest",
 "id": "Actividade1c3325a-33d6-4b9b-bd8f-d21c64944219",
 "dificultad": 2
}